[
  { "kana": "あ", "romaji": "a",   "status": "used",     "category": "standard",   "exclusion_reason": null },
  { "kana": "い", "romaji": "i",   "status": "used",     "category": "standard",   "exclusion_reason": null },
  { "kana": "う", "romaji": "u",   "status": "used",     "category": "standard",   "exclusion_reason": null },
  { "kana": "え", "romaji": "e",   "status": "used",     "category": "standard",   "exclusion_reason": null },
  { "kana": "お", "romaji": "o",   "status": "excluded", "category": "visual",     "exclusion_reason": "「あ」との字形混同リスク" },
  { "kana": "か", "romaji": "ka",  "status": "used",     "category": "standard",   "exclusion_reason": null },
  { "kana": "き", "romaji": "ki",  "status": "used",     "category": "standard",   "exclusion_reason": null },
  { "kana": "く", "romaji": "ku",  "status": "used",     "category": "standard",   "exclusion_reason": null },
  { "kana": "け", "romaji": "ke",  "status": "used",     "category": "standard",   "exclusion_reason": null },
  { "kana": "こ", "romaji": "ko",  "status": "used",     "category": "standard",   "exclusion_reason": null },
  { "kana": "さ", "romaji": "sa",  "status": "used",     "category": "standard",   "exclusion_reason": null },
  { "kana": "し", "romaji": "si",  "status": "used",     "category": "standard",   "exclusion_reason": null },
  { "kana": "す", "romaji": "su",  "status": "used",     "category": "standard",   "exclusion_reason": null },
  { "kana": "せ", "romaji": "se",  "status": "used",     "category": "standard",   "exclusion_reason": null },
  { "kana": "そ", "romaji": "so",  "status": "used",     "category": "standard",   "exclusion_reason": null },
  { "kana": "た", "romaji": "ta",  "status": "used",     "category": "standard",   "exclusion_reason": null },
  { "kana": "ち", "romaji": "ti",  "status": "used",     "category": "standard",   "exclusion_reason": null },
  { "kana": "つ", "romaji": "tu",  "status": "used",     "category": "standard",   "exclusion_reason": null },
  { "kana": "て", "romaji": "te",  "status": "used",     "category": "standard",   "exclusion_reason": null },
  { "kana": "と", "romaji": "to",  "status": "excluded", "category": "visual",     "exclusion_reason": "「う」との字形混同リスク（手書きで紛らわしい）" },
  { "kana": "な", "romaji": "na",  "status": "used",     "category": "standard",   "exclusion_reason": null },
  { "kana": "に", "romaji": "ni",  "status": "used",     "category": "standard",   "exclusion_reason": null },
  { "kana": "ぬ", "romaji": "nu",  "status": "used",     "category": "standard",   "exclusion_reason": null },
  { "kana": "ね", "romaji": "ne",  "status": "used",     "category": "standard",   "exclusion_reason": null },
  { "kana": "の", "romaji": "no",  "status": "excluded", "category": "semantic",   "exclusion_reason": "「〜の」と読めるため所有格と誤読される可能性。外交用途にも予約済み" },
  { "kana": "は", "romaji": "ha",  "status": "used",     "category": "standard",   "exclusion_reason": null },
  { "kana": "ひ", "romaji": "hi",  "status": "used",     "category": "standard",   "exclusion_reason": null },
  { "kana": "ふ", "romaji": "fu",  "status": "used",     "category": "standard",   "exclusion_reason": null },
  { "kana": "へ", "romaji": "he",  "status": "excluded", "category": "visual",     "exclusion_reason": "カタカナ「へ」と字形が同一で判読不能" },
  { "kana": "ほ", "romaji": "ho",  "status": "used",     "category": "standard",   "exclusion_reason": null },
  { "kana": "ま", "romaji": "ma",  "status": "used",     "category": "standard",   "exclusion_reason": null },
  { "kana": "み", "romaji": "mi",  "status": "used",     "category": "standard",   "exclusion_reason": null },
  { "kana": "む", "romaji": "mu",  "status": "used",     "category": "standard",   "exclusion_reason": null },
  { "kana": "め", "romaji": "me",  "status": "used",     "category": "standard",   "exclusion_reason": null },
  { "kana": "も", "romaji": "mo",  "status": "used",     "category": "standard",   "exclusion_reason": null },
  { "kana": "や", "romaji": "ya",  "status": "used",     "category": "standard",   "exclusion_reason": null },
  { "kana": "ゆ", "romaji": "yu",  "status": "used",     "category": "standard",   "exclusion_reason": null },
  { "kana": "よ", "romaji": "yo",  "status": "used",     "category": "standard",   "exclusion_reason": null },
  { "kana": "ら", "romaji": "ra",  "status": "used",     "category": "standard",   "exclusion_reason": null },
  { "kana": "り", "romaji": "ri",  "status": "used",     "category": "standard",   "exclusion_reason": null },
  { "kana": "る", "romaji": "ru",  "status": "used",     "category": "standard",   "exclusion_reason": null },
  { "kana": "れ", "romaji": "re",  "status": "used",     "category": "standard",   "exclusion_reason": null },
  { "kana": "ろ", "romaji": "ro",  "status": "used",     "category": "standard",   "exclusion_reason": null },
  { "kana": "わ", "romaji": "wa",  "status": "used",     "category": "standard",   "exclusion_reason": null },
  { "kana": "を", "romaji": "wo",  "status": "excluded", "category": "semantic",   "exclusion_reason": "助詞・目的格として読まれるため不採用。事業用（緑ナンバー）専用に一部割当" },
  { "kana": "ん", "romaji": "n",   "status": "excluded", "category": "phonetic",   "exclusion_reason": "単独で音節を持たず、前後の音を変化させるため判読・発音困難" }
]
